oarepo_micro_api/__init__.py
oarepo_micro_api/alias_prefix_replacer.py
oarepo_micro_api/cli.py
oarepo_micro_api/config.py
oarepo_micro_api/signals.py
oarepo_micro_api/utils.py
oarepo_micro_api/version.py
oarepo_micro_api/wsgi.py
tests/__init__.py
tests/conftest.py
tests/test_app_version.py
tests/api/__init__.py
tests/api/conftest.py
tests/api/test_api_wellknown.py
tests/api/test_cli.py
tests/api/test_utils.py
oarepo_micro_api-3.5.67.dist-info/AUTHORS.rst
oarepo_micro_api-3.5.67.dist-info/LICENSE
oarepo_micro_api-3.5.67.dist-info/METADATA
oarepo_micro_api-3.5.67.dist-info/WHEEL
oarepo_micro_api-3.5.67.dist-info/entry_points.txt
oarepo_micro_api-3.5.67.dist-info/top_level.txt
oarepo_micro_api-3.5.67.dist-info/RECORD
