Metadata-Version: 2.1
Name: oarepo-micro-api
Version: 3.5.67
Summary: OARepo REST API microservice
Home-page: https://github.com/oarepo/oarepo-micro-api
Author: Miroslav Bauer @ CESNET
Author-email: bauer@cesnet.cz
License: MIT
Keywords: oarepo-micro-api Invenio
Platform: any
Classifier: Environment :: Web Environment
Classifier: Intended Audience :: Developers
Classifier: License :: OSI Approved :: MIT License
Classifier: Operating System :: OS Independent
Classifier: Programming Language :: Python
Classifier: Topic :: Internet :: WWW/HTTP :: Dynamic Content
Classifier: Programming Language :: Python :: 3
Classifier: Programming Language :: Python :: 3.6
Classifier: Development Status :: 3 - Alpha
License-File: LICENSE
License-File: AUTHORS.rst
Requires-Dist: oarepo (~=3.5.73)
Requires-Dist: oarepo-heartbeat (>=1.0.2)
Requires-Dist: importlib-metadata
Requires-Dist: uwsgi (>=2.0)
Requires-Dist: uwsgi-tools (>=1.1.1)
Requires-Dist: uwsgitop (>=0.11)
Requires-Dist: wrapt (<2.0.0,>=1.12.1)
Provides-Extra: tests
Requires-Dist: webtest ; extra == 'tests'
Requires-Dist: pytest-pycodestyle ; extra == 'tests'
Requires-Dist: pipdeptree ; extra == 'tests'
Requires-Dist: oarepo[tests] (~=3.5.73) ; extra == 'tests'
